pilotlight_build/__init__.py
pilotlight_build/pl_build.py
pilotlight_build-0.11.0.dist-info/LICENSE
pilotlight_build-0.11.0.dist-info/METADATA
pilotlight_build-0.11.0.dist-info/WHEEL
pilotlight_build-0.11.0.dist-info/top_level.txt
pilotlight_build-0.11.0.dist-info/RECORD
